{"metadata": {"data_version": "6", "match_id": "NA1_5472781209", "participants": ["OMFjH8VbgJWNo9G3kvlOudmn2ao1KNI_8Rk8XLyFeculHHxtepwjPQ_Gzpjzhi0LYeX5m3Ds-f--bg", "KuBZSA63qsKaGvp5zZ4u3Kb4d9iMqhw9a3xHqSjku-ufs8Sb_WECBDOyOZ0RUttzkPQtAB8spMrlUg", "Ac3ts2-pgg0K6X9-ar9KLxy0WyXxtu-K4ytByKWoRgdu5ElfL3awTuwxuVXd7WrvrBqUcosyrU_DUw", "0bf0BpWOSzhXQ8qoV4UfQc2THvwAkmXVydIRNOmUCRm5i-CypBp-cJvgwBxafDuwnC0p0K1a_zRKHw", "NvaFJ2_Bw4RaHBYZCL1CwNsZ7Et6ld39L_iYEXDBuMDA9keE0J0tH6Kbh5k9VuF3AFWCNYlAS01llw", "-6nY1u-9Y0VFOTziGRDdFAZuAVtiUes_l8nLVsyvOdqQ0iCgBvESqw6ewQp8q5Bakwr0_Lg9rdfuhQ", "l7BgbxhdOLEuqrVpWHz3V5rjC1v18C04IWyMsG-InMbptEJYDAppoCpQJScP32u2BUXNAtEWtIPyLQ", "X1suXalTXpbU88tA8tAEtAQuDwCGqj7JzP6HCUkn7F6r-DTz0ILQII_xgTlH1Mr3Ypc6RpoI6LId0w"]}, "info": {"endOfGameResult": "GameComplete", "gameCreation": 1769221127000, "gameId": 5472781209, "game_datetime": 1769223235798, "game_length": 2071.5712890625, "game_version": "Linux Version 16.2.740.1491 (Jan 21 2026/11:19:28) [PUBLIC] <Releases/16.2>", "mapId": 22, "participants": [{"companion": {"content_ID": "ab37883f-9dab-4e3c-a856-5e5aefed04df", "item_ID": 149002, "skin_ID": 2, "species": "PetStyleTwoIrelia"}, "gold_left": 28, "last_round": 31, "level": 7, "missions": {"PlayerScore2": 94}, "partner_group_id": 3, "placement": 7, "players_eliminated": 0, "puuid": "OMFjH8VbgJWNo9G3kvlOudmn2ao1KNI_8Rk8XLyFeculHHxtepwjPQ_Gzpjzhi0LYeX5m3Ds-f--bg", "riotIdGameName": "KarmaYame", "riotIdTagline": "NA1", "time_eliminated": 1888.0189208984375, "total_damage_to_players": 48, "traits": [{"name": "TFT16_Brawler", "num_units": 2, "style": 1, "tier_current": 1, "tier_total": 3}, {"name": "TFT16_Defender", "num_units": 1, "style": 0, "tier_current": 0, "tier_total": 3}, {"name": "TFT16_Gunslinger", "num_units": 1, "style": 0, "tier_current": 0, "tier_total": 2}, {"name": "TFT16_Ionia", "num_units": 7, "style": 4, "tier_current": 3, "tier_total": 4}, {"name": "TFT16_Rapidfire", "num_units": 1, "style": 0, "tier_current": 0, "tier_total": 4}, {"name": "TFT16_Slayer", "num_units": 1, "style": 0, "tier_current": 0, "tier_total": 3}, {"name": "TFT16_Sorcerer", "num_units": 1, "style": 0, "tier_current": 0, "tier_total": 3}, {"name": "TFT16_Yordle", "num_units": 1, "style": 0, "tier_current": 0, "tier_total": 5}], "units": [{"character_id": "TFT16_Shen", "itemNames": [], "name": "", "rarity": 0, "tier": 2}, {"character_id": "TFT16_Jhin", "itemNames": [], "name": "", "rarity": 0, "tier": 3}, {"character_id": "TFT16_Yasuo", "itemNames": ["TFT_Item_JeweledGauntlet", "TFT_Item_GiantsBelt"], "name": "", "rarity": 1, "tier": 3}, {"character_id": "TFT16_Ahri", "itemNames": ["TFT_Item_BlueBuff", "TFT_Item_JeweledGauntlet", "TFT_Item_StatikkShiv"], "name": "", "rarity": 2, "tier": 2}, {"character_id": "TFT16_Kennen", "itemNames": [], "name": "", "rarity": 2, "tier": 2}, {"character_id": "TFT16_Wukong", "itemNames": ["TFT_Item_WarmogsArmor", "TFT_Item_FrozenHeart", "TFT_Item_RedBuff"], "name": "", "rarity": 4, "tier": 2}, {"character_id": "TFT16_Yunara", "itemNames": ["TFT_Item_GuinsoosRageblade", "TFT_Item_InfinityEdge", "TFT_Item_Artifact_NavoriFlickerblades"], "name": "", "rarity": 4, "tier": 2}], "win": false}, {"companion": {"content_ID": "a4a35782-fbae-45ee-bc0d-90c26269d1a9", "item_ID": 27018, "skin_ID": 18, "species": "PetChoncc"}, "gold_left": 0, "last_round": 31, "level": 8, "missions": {"PlayerScore2": 94}, "partner_group_id": 3, "placement": 8, "players_eliminated": 0, "puuid": "KuBZSA63qsKaGvp5zZ4u3Kb4d9iMqhw9a3xHqSjku-ufs8Sb_WECBDOyOZ0RUttzkPQtAB8spMrlUg", "riotIdGameName": "Spedicey", "riotIdTagline": "NA1", "time_eliminated": 1884.764404296875, "total_damage_to_players": 44, "traits": [{"name": "TFT16_Brawler", "num_units": 2, "style": 1, "tier_current": 1, "tier_total": 3}, {"name": "TFT16_Freljord", "num_units": 1, "style": 0, "tier_current": 0, "tier_total": 3}, {"name": "TFT16_Juggernaut", "num_units": 2, "style": 1, "tier_current": 1, "tier_total": 3}, {"name": "TFT16_KaisaUnique", "num_units": 1, "style": 3, "tier_current": 1, "tier_total": 1}, {"name": "TFT16_Longshot", "num_units": 2, "style": 1, "tier_current": 1, "tier_total": 4}, {"name": "TFT16_Noxus", "num_units": 1, "style": 0, "tier_current": 0, "tier_total": 4}, {"name": "TFT16_Slayer", "num_units": 1, "style": 0, "tier_current": 0, "tier_total": 3}, {"name": "TFT16_Sorcerer", "num_units": 2, "style": 1, "tier_current": 1, "tier_total": 3}, {"name": "TFT16_Vanquisher", "num_units": 1, "style": 0, "tier_current": 0, "tier_total": 4}, {"name": "TFT16_Void", "num_units": 6, "style": 4, "tier_current": 3, "tier_total": 4}], "units": [{"character_id": "TFT16_KogMaw", "itemNames": ["TFT_Item_HextechGunblade", "TFT_Item_JeweledGauntlet", "TFT_Item_GuinsoosRageblade"], "name": "", "rarity": 0, "tier": 3}, {"character_id": "TFT16_RekSai", "itemNames": [], "name": "", "rarity": 1, "tier": 2}, {"character_id": "TFT16_ChoGath", "itemNames": ["TFT_Item_Redemption", "TFT_Item_WarmogsArmor", "TFT_Item_IonicSpark"], "name": "", "rarity": 1, "tier": 3}, {"character_id": "TFT16_BelVeth", "itemNames": ["TFT_Item_InfinityEdge"], "name": "", "rarity": 4, "tier": 2}, {"character_id": "TFT16_RiftHerald", "itemNames": [], "name": "", "rarity": 4, "tier": 2}, {"character_id": "TFT16_Kaisa", "itemNames": [], "name": "", "rarity": 4, "tier": 1}, {"character_id": "TFT16_Swain", "itemNames": ["TFT_Item_NeedlesslyLargeRod"], "name": "", "rarity": 4, "tier": 2}, {"character_id": "TFT16_Volibear", "itemNames": [], "name": "", "rarity": 6, "tier": 1}], "win": false}, {"companion": {"content_ID": "42f00aaf-97d5-4c5a-a0e1-c904818a74a8", "item_ID": 14027, "skin_ID": 27, "species": "PetQiyanaDog"}, "gold_left": 5, "last_round": 34, "level": 10, "missions": {"PlayerScore2": 206}, "partner_group_id": 1, "placement": 4, "players_eliminated": 2, "puuid": "Ac3ts2-pgg0K6X9-ar9KLxy0WyXxtu-K4ytByKWoRgdu5ElfL3awTuwxuVXd7WrvrBqUcosyrU_DUw", "riotIdGameName": "Cross Hard", "riotIdTagline": "NA1", "time_eliminated": 2062.799072265625, "total_damage_to_players": 64, "traits": [{"name": "TFT16_Blacksmith", "num_units": 1, "style": 3, "tier_current": 1, "tier_total": 1}, {"name": "TFT16_Demacia", "num_units": 1, "style": 0, "tier_current": 0, "tier_total": 4}, {"name": "TFT16_Freljord", "num_units": 1, "style": 0, "tier_current": 0, "tier_total": 3}, {"name": "TFT16_Harvester", "num_units": 1, "style": 3, "tier_current": 1, "tier_total": 1}, {"name": "TFT16_Ionia", "num_units": 1, "style": 0, "tier_current": 0, "tier_total": 4}, {"name": "TFT16_Juggernaut", "num_units": 1, "style": 0, "tier_current": 0, "tier_total": 3}, {"name": "TFT16_Magus", "num_units": 1, "style": 0, "tier_current": 0, "tier_total": 2}, {"name": "TFT16_Rapidfire", "num_units": 1, "style": 0, "tier_current": 0, "tier_total": 4}, {"name": "TFT16_ShadowIsles", "num_units": 5, "style": 4, "tier_current": 4, "tier_total": 4}, {"name": "TFT16_ShyvanaUnique", "num_units": 1, "style": 3, "tier_current": 1, "tier_total": 1}, {"name": "TFT16_Vanquisher", "num_units": 2, "style": 1, "tier_current": 1, "tier_total": 4}, {"name": "TFT16_Warden", "num_units": 5, "style": 4, "tier_current": 4, "tier_total": 4}], "units": [{"character_id": "TFT16_Viego", "itemNames": [], "name": "", "rarity": 0, "tier": 2}, {"character_id": "TFT16_XinZhao", "itemNames": [], "name": "", "rarity": 1, "tier": 2}, {"character_id": "TFT16_Yorick", "itemNames": [], "name": "", "rarity": 1, "tier": 1}, {"character_id": "TFT16_Gwen", "itemNames": [], "name": "", "rarity": 2, "tier": 1}, {"character_id": "TFT16_Braum", "itemNames": ["TFT_Item_GiantsBelt", "TFT_Item_SpectralGauntlet"], "name": "", "rarity": 4, "tier": 2}, {"character_id": "TFT16_Kalista", "itemNames": ["TFT_Item_Artifact_Fishbones", "TFT_Item_LastWhisper", "TFT_Item_SpearOfShojin"], "name": "", "rarity": 4, "tier": 2}, {"character_id": "TFT16_Ornn", "itemNames": [], "name": "", "rarity": 6, "tier": 1}, {"character_id": "TFT16_Fiddlesticks", "itemNames": ["TFT_Item_JeweledGauntlet"], "name": "", "rarity": 6, "tier": 2}, {"character_id": "TFT16_Shyvana", "itemNames": ["TFT_Item_Bloodthirster"], "name": "", "rarity": 6, "tier": 2}, {"character_id": "TFT16_Thresh", "itemNames": ["TFT_Item_UnstableConcoction", "TFT_Item_ArchangelsStaff", "TFT_Item_ArchangelsStaff"], "name": "", "rarity": 6, "tier": 2}], "win": true}, {"companion": {"content_ID": "e69f4403-c591-47c0-8cb2-4693b52ff076", "item_ID": 107002, "skin_ID": 2, "species": "PetStyleTwoJhin"}, "gold_left": 4, "last_round": 34, "level": 8, "missions": {"PlayerScore2": 206}, "partner_group_id": 1, "placement": 3, "players_eliminated": 3, "puuid": "0bf0BpWOSzhXQ8qoV4UfQc2THvwAkmXVydIRNOmUCRm5i-CypBp-cJvgwBxafDuwnC0p0K1a_zRKHw", "riotIdGameName": "Buhhblam", "riotIdTagline": "NA1", "time_eliminated": 2063.299560546875, "total_damage_to_players": 70, "traits": [{"name": "TFT16_Bilgewater", "num_units": 7, "style": 4, "tier_current": 3, "tier_total": 4}, {"name": "TFT16_Blacksmith", "num_units": 1, "style": 3, "tier_current": 1, "tier_total": 1}, {"name": "TFT16_Brawler", "num_units": 2, "style": 1, "tier_current": 1, "tier_total": 3}, {"name": "TFT16_DarkinWeapon", "num_units": 1, "style": 1, "tier_current": 1, "tier_total": 3}, {"name": "TFT16_Glutton", "num_units": 1, "style": 3, "tier_current": 1, "tier_total": 1}, {"name": "TFT16_Gunslinger", "num_units": 2, "style": 1, "tier_current": 1, "tier_total": 2}, {"name": "TFT16_Juggernaut", "num_units": 1, "style": 0, "tier_current": 0, "tier_total": 3}, {"name": "TFT16_Rapidfire", "num_units": 1, "style": 0, "tier_current": 0, "tier_total": 4}, {"name": "TFT16_Warden", "num_units": 2, "style": 1, "tier_current": 1, "tier_total": 4}, {"name": "TFT16_Yordle", "num_units": 1, "style": 0, "tier_current": 0, "tier_total": 5}], "units": [{"character_id": "TFT16_Illaoi", "itemNames": [], "name": "", "rarity": 0, "tier": 2}, {"character_id": "TFT16_TwistedFate", "itemNames": ["TFT_Item_RapidFireCannon", "TFT_Item_Leviathan", "TFT_Item_GuinsoosRageblade"], "name": "", "rarity": 1, "tier": 2}, {"character_id": "TFT16_Graves", "itemNames": [], "name": "", "rarity": 1, "tier": 2}, {"character_id": "TFT16_Nautilus", "itemNames": ["TFT_Item_GargoyleStoneplate", "TFT16_Item_Bilgewater_FreebootersFrock", "TFT_Item_FrozenHeart"], "name": "", "rarity": 2, "tier": 3}, {"character_id": "TFT16_MissFortune", "itemNames": ["TFT16_Item_Bilgewater_FirstMatesFlintlock", "TFT_Item_BlueBuff", "TFT4_Item_OrnnTheCollector"], "name": "", "rarity": 4, "tier": 3}, {"character_id": "TFT16_Fizz", "itemNames": ["TFT_Item_Bloodthirster", "TFT_Item_TitansResolve", "TFT_Item_JeweledGauntlet"], "name": "", "rarity": 4, "tier": 2}, {"character_id": "TFT16_Ornn", "itemNames": [], "name": "", "rarity": 6, "tier": 2}, {"character_id": "TFT16_TahmKench", "itemNames": ["TFT_Item_DragonsClaw", "TFT_Item_SpectralGauntlet", "TFT16_TheDarkinBow"], "name": "", "rarity": 6, "tier": 2}], "win": true}, {"companion": {"content_ID": "a0e9be28-3406-41d4-adac-26af1b15e5be", "item_ID": 133002, "skin_ID": 2, "species": "PetStyleTwoAhri"}, "gold_left": 3, "last_round": 34, "level": 10, "missions": {"PlayerScore2": 206}, "partner_group_id": 2, "placement": 2, "players_eliminated": 1, "puuid": "NvaFJ2_Bw4RaHBYZCL1CwNsZ7Et6ld39L_iYEXDBuMDA9keE0J0tH6Kbh5k9VuF3AFWCNYlAS01llw", "riotIdGameName": "Glucose Guardian", "riotIdTagline": "A1C", "time_eliminated": 2063.299560546875, "total_damage_to_players": 49, "traits": [{"name": "TFT16_Brawler", "num_units": 2, "style": 1, "tier_current": 1, "tier_total": 3}, {"name": "TFT16_Defender", "num_units": 2, "style": 1, "tier_current": 1, "tier_total": 3}, {"name": "TFT16_Demacia", "num_units": 1, "style": 0, "tier_current": 0, "tier_total": 4}, {"name": "TFT16_Harvester", "num_units": 1, "style": 3, "tier_current": 1, "tier_total": 1}, {"name": "TFT16_Ionia", "num_units": 7, "style": 4, "tier_current": 3, "tier_total": 4}, {"name": "TFT16_KindredUnique", "num_units": 1, "style": 3, "tier_current": 1, "tier_total": 1}, {"name": "TFT16_Rapidfire", "num_units": 2, "style": 1, "tier_current": 1, "tier_total": 4}, {"name": "TFT16_Slayer", "num_units": 2, "style": 1, "tier_current": 1, "tier_total": 3}, {"name": "TFT16_TheBoss", "num_units": 1, "style": 3, "tier_current": 1, "tier_total": 1}, {"name": "TFT16_Vanquisher", "num_units": 1, "style": 0, "tier_current": 0, "tier_total": 4}, {"name": "TFT16_Yordle", "num_units": 1, "style": 0, "tier_current": 0, "tier_total": 5}], "units": [{"character_id": "TFT16_Shen", "itemNames": [], "name": "", "rarity": 0, "tier": 2}, {"character_id": "TFT16_Yasuo", "itemNames": ["TFT_Item_UnstableConcoction", "TFT_Item_GuardianAngel", "TFT_Item_InfinityEdge"], "name": "", "rarity": 1, "tier": 3}, {"character_id": "TFT16_Kennen", "itemNames": [], "name": "", "rarity": 2, "tier": 2}, {"character_id": "TFT16_Garen", "itemNames": [], "name": "", "rarity": 4, "tier": 1}, {"character_id": "TFT16_Wukong", "itemNames": ["TFT_Item_Artifact_LightshieldCrest"], "name": "", "rarity": 4, "tier": 2}, {"character_id": "TFT16_Yone", "itemNames": ["TFT_Item_TitansResolve", "TFT_Item_Bloodthirster", "TFT_Item_SteraksGage"], "name": "", "rarity": 4, "tier": 2}, {"character_id": "TFT16_Yunara", "itemNames": ["TFT_Item_InfinityEdge", "TFT_Item_RunaansHurricane", "TFT_Item_RecurveBow"], "name": "", "rarity": 4, "tier": 2}, {"character_id": "TFT16_Kindred", "itemNames": [], "name": "", "rarity": 6, "tier": 2}, {"character_id": "TFT16_Fiddlesticks", "itemNames": [], "name": "", "rarity": 6, "tier": 1}, {"character_id": "TFT16_Sett", "itemNames": ["TFT_Item_ThiefsGloves", "TFT_Item_EmptyBag", "TFT_Item_EmptyBag"], "name": "", "rarity": 6, "tier": 2}], "win": true}, {"companion": {"content_ID": "153a2b23-16b3-44c7-9e13-093ce2a066a5", "item_ID": 119001, "skin_ID": 1, "species": "PetStyleTwoThresh"}, "gold_left": 0, "last_round": 34, "level": 8, "missions": {"PlayerScore2": 206}, "partner_group_id": 2, "placement": 1, "players_eliminated": 1, "puuid": "-6nY1u-9Y0VFOTziGRDdFAZuAVtiUes_l8nLVsyvOdqQ0iCgBvESqw6ewQp8q5Bakwr0_Lg9rdfuhQ", "riotIdGameName": "Terminal Big Boy", "riotIdTagline": "HEAT", "time_eliminated": 2063.299560546875, "total_damage_to_players": 76, "traits": [{"name": "TFT16_Defender", "num_units": 2, "style": 1, "tier_current": 1, "tier_total": 3}, {"name": "TFT16_Demacia", "num_units": 1, "style": 0, "tier_current": 0, "tier_total": 4}, {"name": "TFT16_Explorer", "num_units": 6, "style": 2, "tier_current": 2, "tier_total": 3}, {"name": "TFT16_Freljord", "num_units": 1, "style": 0, "tier_current": 0, "tier_total": 3}, {"name": "TFT16_Huntress", "num_units": 1, "style": 3, "tier_current": 1, "tier_total": 1}, {"name": "TFT16_Invoker", "num_units": 2, "style": 1, "tier_current": 1, "tier_total": 2}, {"name": "TFT16_Slayer", "num_units": 1, "style": 0, "tier_current": 0, "tier_total": 3}, {"name": "TFT16_Sorcerer", "num_units": 1, "style": 0, "tier_current": 0, "tier_total": 3}, {"name": "TFT16_Targon", "num_units": 1, "style": 4, "tier_current": 1, "tier_total": 1}], "units": [{"character_id": "TFT16_Qiyana", "itemNames": [], "name": "", "rarity": 0, "tier": 2}, {"character_id": "TFT16_Neeko", "itemNames": ["TFT_Item_Redemption", "TFT_Item_BrambleVest", "TFT_Item_GargoyleStoneplate"], "name": "", "rarity": 1, "tier": 2}, {"character_id": "TFT16_Milio", "itemNames": ["TFT_Item_StatikkShiv", "TFT_Item_SparringGloves", "TFT_Item_RapidFireCannon"], "name": "", "rarity": 2, "tier": 2}, {"character_id": "TFT16_Taric", "itemNames": [], "name": "", "rarity": 4, "tier": 2}, {"character_id": "TFT16_Garen", "itemNames": [], "name": "", "rarity": 4, "tier": 2}, {"character_id": "TFT16_Lissandra", "itemNames": ["TFT_Item_ForceOfNature"], "name": "", "rarity": 4, "tier": 2}, {"character_id": "TFT16_Nidalee", "itemNames": ["TFT_Item_UnstableConcoction", "TFT_Item_JeweledGauntlet", "TFT_Item_UnstableConcoction"], "name": "", "rarity": 4, "tier": 2}, {"character_id": "TFT16_Skarner", "itemNames": ["TFT_Item_GargoyleStoneplate", "TFT_Item_Redemption"], "name": "", "rarity": 4, "tier": 2}, {"character_id": "TFT16_Brock", "itemNames": ["TFT5_Item_ThiefsGlovesRadiant", "TFT5_Item_HextechGunbladeRadiant", "TFT5_Item_MorellonomiconRadiant"], "name": "", "rarity": 7, "tier": 1}], "win": true}, {"companion": {"content_ID": "0271d879-6ab8-4111-b349-6fc98710ad07", "item_ID": 108002, "skin_ID": 2, "species": "PetChibiJanna"}, "gold_left": 0, "last_round": 31, "level": 8, "missions": {"PlayerScore2": 94}, "partner_group_id": 4, "placement": 6, "players_eliminated": 1, "puuid": "l7BgbxhdOLEuqrVpWHz3V5rjC1v18C04IWyMsG-InMbptEJYDAppoCpQJScP32u2BUXNAtEWtIPyLQ", "riotIdGameName": "Honestly", "riotIdTagline": "befr", "time_eliminated": 1894.9285888671875, "total_damage_to_players": 47, "traits": [{"name": "TFT16_Brawler", "num_units": 2, "style": 1, "tier_current": 1, "tier_total": 3}, {"name": "TFT16_Freljord", "num_units": 1, "style": 0, "tier_current": 0, "tier_total": 3}, {"name": "TFT16_Juggernaut", "num_units": 2, "style": 1, "tier_current": 1, "tier_total": 3}, {"name": "TFT16_KaisaUnique", "num_units": 1, "style": 3, "tier_current": 1, "tier_total": 1}, {"name": "TFT16_Longshot", "num_units": 2, "style": 1, "tier_current": 1, "tier_total": 4}, {"name": "TFT16_Magus", "num_units": 1, "style": 0, "tier_current": 0, "tier_total": 2}, {"name": "TFT16_Noxus", "num_units": 1, "style": 0, "tier_current": 0, "tier_total": 4}, {"name": "TFT16_Sorcerer", "num_units": 2, "style": 1, "tier_current": 1, "tier_total": 3}, {"name": "TFT16_Vanquisher", "num_units": 1, "style": 0, "tier_current": 0, "tier_total": 4}, {"name": "TFT16_Void", "num_units": 6, "style": 4, "tier_current": 3, "tier_total": 4}], "units": [{"character_id": "TFT16_KogMaw", "itemNames": [], "name": "", "rarity": 0, "tier": 1}, {"character_id": "TFT16_RekSai", "itemNames": [], "name": "", "rarity": 1, "tier": 1}, {"character_id": "TFT16_ChoGath", "itemNames": [], "name": "", "rarity": 1, "tier": 2}, {"character_id": "TFT16_Malzahar", "itemNames": ["TFT_Item_Artifact_BlightingJewel"], "name": "", "rarity": 2, "tier": 2}, {"character_id": "TFT16_RiftHerald", "itemNames": ["TFT_Item_BrambleVest", "TFT_Item_DragonsClaw", "TFT_Item_Redemption"], "name": "", "rarity": 4, "tier": 2}, {"character_id": "TFT16_Kaisa", "itemNames": ["TFT_Item_SpearOfShojin", "TFT_Item_InfinityEdge", "TFT_Item_LastWhisper"], "name": "", "rarity": 4, "tier": 2}, {"character_id": "TFT16_Swain", "itemNames": ["TFT_Item_Redemption"], "name": "", "rarity": 4, "tier": 2}, {"character_id": "TFT16_Volibear", "itemNames": ["TFT_Item_Artifact_WitsEnd", "TFT_Item_GuardianAngel"], "name": "", "rarity": 6, "tier": 1}], "win": false}, {"companion": {"content_ID": "5601b81d-dfe2-40d7-81c5-4795ac9f6f3f", "item_ID": 91002, "skin_ID": 2, "species": "PetChibiOrianna"}, "gold_left": 5, "last_round": 31, "level": 9, "missions": {"PlayerScore2": 94}, "partner_group_id": 4, "placement": 5, "players_eliminated": 1, "puuid": "X1suXalTXpbU88tA8tAEtAQuDwCGqj7JzP6HCUkn7F6r-DTz0ILQII_xgTlH1Mr3Ypc6RpoI6LId0w", "riotIdGameName": "Bassel", "riotIdTagline": "001", "time_eliminated": 1898.0328369140625, "total_damage_to_players": 59, "traits": [{"name": "TFT16_AurelionSolUnique", "num_units": 1, "style": 3, "tier_current": 1, "tier_total": 1}, {"name": "TFT16_Harvester", "num_units": 1, "style": 3, "tier_current": 1, "tier_total": 1}, {"name": "TFT16_Juggernaut", "num_units": 1, "style": 0, "tier_current": 0, "tier_total": 3}, {"name": "TFT16_ShyvanaUnique", "num_units": 1, "style": 3, "tier_current": 1, "tier_total": 1}, {"name": "TFT16_Targon", "num_units": 6, "style": 4, "tier_current": 1, "tier_total": 1}, {"name": "TFT16_Vanquisher", "num_units": 1, "style": 0, "tier_current": 0, "tier_total": 4}], "units": [{"character_id": "TFT16_Aphelios", "itemNames": [], "name": "", "rarity": 1, "tier": 2}, {"character_id": "TFT16_Zoe", "itemNames": ["TFT_Item_SpearOfShojin", "TFT_Item_ArchangelsStaff"], "name": "", "rarity": 2, "tier": 2}, {"character_id": "TFT16_Leona", "itemNames": [], "name": "", "rarity": 2, "tier": 2}, {"character_id": "TFT16_Taric", "itemNames": ["TFT_Item_RedBuff", "TFT_Item_AdaptiveHelm", "TFT_Item_GargoyleStoneplate"], "name": "", "rarity": 4, "tier": 2}, {"character_id": "TFT16_Taric", "itemNames": [], "name": "", "rarity": 4, "tier": 2}, {"character_id": "TFT16_Diana", "itemNames": ["TFT_Item_ThiefsGloves", "TFT_Item_RunaansHurricane", "TFT_Item_Quicksilver"], "name": "", "rarity": 4, "tier": 2}, {"character_id": "TFT16_Fiddlesticks", "itemNames": [], "name": "", "rarity": 6, "tier": 1}, {"character_id": "TFT16_Shyvana", "itemNames": [], "name": "", "rarity": 6, "tier": 1}, {"character_id": "TFT16_AurelionSol", "itemNames": ["TFT_Item_Leviathan", "TFT_Item_SpearOfShojin", "TFT_Item_JeweledGauntlet"], "name": "", "rarity": 7, "tier": 2}], "win": false}], "queueId": 1160, "queue_id": 1160, "tft_game_type": "pairs", "tft_set_core_name": "TFTSet16", "tft_set_number": 16}}