{"metadata": {"data_version": "6", "match_id": "NA1_5474146105", "participants": ["IzyRpFKWDC7AzyB6Dh3WI8w06PDk9yc4Z9MMXXK_zNAqB-JgZr6kQrxnmWSr3bA_f7hs71BpJn3kLQ", "VJb-HCG57UiSBPcSlNTJ95geq_ilMvjxdx5OXG4xxBTu-nkgMmBprkJb8urdYViCZnFeVF6BHMTcpw", "Ubpayed4aLwrUpjGE5qgoR32ykGZaQZGm9GPnP4RrhTcdesoWDZnzXdNn4il6NsZNasZAQXBWJz_jw", "I2OgAZVPq_KZdV6TqGSy_CVVxzHLpgaTqS31K-W5Xe72-IyHBRYnhYkKjyqySL-nD8RD1dfhLaW5pg", "LtBHVR9fYTm9XPY9FQyYjQKBub5JkwbsccrNCPINWCzYi-236HdZIaN2AeY3gbhf-FTsASYxb6bC2A", "TRz6ikl7t3N3uaNKJMGfc1bIpg7yhaRRdGJeuvT3kcdnvneaZ-m13sjl6g9X6dyBCb13_FNAvI-HQg", "Bxy0YkkQBHWuzwUvyWEd9LXlamH4XKhkUO7z1uNSmCiyqL-ruw8HhJcrfNVT1NSoVfCda2_eYJxe5Q", "EWXJG0pWwM-xE5QIDIchT7O6JjFGuqoF6zX0Aa_F6QfgZm45m0DREpkApgktQdztEpHQum8WuR9OMQ"]}, "info": {"endOfGameResult": "GameComplete", "gameCreation": 1769322323000, "gameId": 5474146105, "game_datetime": 1769324523196, "game_length": 2149.581298828125, "game_version": "Linux Version 16.2.740.1491 (Jan 21 2026/11:19:28) [PUBLIC] <Releases/16.2>", "mapId": 22, "participants": [{"companion": {"content_ID": "5897ad9f-4665-4372-8f3e-6c878adb8918", "item_ID": 1, "skin_ID": 1, "species": "PetTFTAvatar"}, "gold_left": 68, "last_round": 26, "level": 9, "missions": {"PlayerScore2": 75}, "placement": 7, "players_eliminated": 0, "puuid": "IzyRpFKWDC7AzyB6Dh3WI8w06PDk9yc4Z9MMXXK_zNAqB-JgZr6kQrxnmWSr3bA_f7hs71BpJn3kLQ", "riotIdGameName": "Yyanjing08god121", "riotIdTagline": "Yu0", "skill_tree": {"EventSkill_DemotionProtection": 0, "EventSkill_PlacementDelta": 100}, "time_eliminated": 1506.3935546875, "total_damage_to_players": 31, "traits": [{"name": "TFT4_Adept", "num_units": 2, "style": 1, "tier_current": 1, "tier_total": 3}, {"name": "TFT4_Brawler", "num_units": 2, "style": 1, "tier_current": 1, "tier_total": 4}, {"name": "TFT4_Divine", "num_units": 1, "style": 0, "tier_current": 0, "tier_total": 4}, {"name": "TFT4_Elderwood", "num_units": 6, "style": 2, "tier_current": 2, "tier_total": 3}, {"name": "TFT4_Emperor", "num_units": 1, "style": 3, "tier_current": 1, "tier_total": 1}, {"name": "TFT4_Enlightened", "num_units": 1, "style": 0, "tier_current": 0, "tier_total": 4}, {"name": "TFT4_Executioner", "num_units": 1, "style": 0, "tier_current": 0, "tier_total": 3}, {"name": "TFT4_Exile", "num_units": 1, "style": 1, "tier_current": 1, "tier_total": 2}, {"name": "TFT4_Keeper", "num_units": 3, "style": 1, "tier_current": 1, "tier_total": 4}, {"name": "TFT4_Mage", "num_units": 1, "style": 0, "tier_current": 0, "tier_total": 4}, {"name": "TFT4_Warlord", "num_units": 1, "style": 0, "tier_current": 0, "tier_total": 4}], "units": [{"character_id": "TFT4_Maokai", "itemNames": ["TFT_Item_GargoyleStoneplate", "TFT_Item_RedBuff"], "name": "", "rarity": 0, "tier": 3}, {"character_id": "TFT4_Rakan", "itemNames": [], "name": "", "rarity": 1, "tier": 2}, {"character_id": "TFT4_Irelia", "itemNames": [], "name": "", "rarity": 2, "tier": 1}, {"character_id": "TFT4_Nunu", "itemNames": [], "name": "", "rarity": 2, "tier": 2}, {"character_id": "TFT4_Veigar", "itemNames": [], "name": "", "rarity": 2, "tier": 1}, {"character_id": "TFT4_Xayah", "itemNames": [], "name": "", "rarity": 4, "tier": 1}, {"character_id": "TFT4_Azir", "itemNames": [], "name": "", "rarity": 6, "tier": 1}, {"character_id": "TFT4_Yone", "itemNames": ["TFT_Item_MadredsBloodrazor", "TFT_Item_JeweledGauntlet", "TFT_Item_RabadonsDeathcap"], "name": "", "rarity": 6, "tier": 2}, {"character_id": "TFT4_AzirSoldier", "itemNames": [], "name": "", "rarity": 6, "tier": 1}, {"character_id": "TFT4_AzirSoldier", "itemNames": [], "name": "", "rarity": 6, "tier": 1}], "win": false}, {"companion": {"content_ID": "2fc3a4c0-7322-4ef5-b434-0cea1d1997e6", "item_ID": 35001, "skin_ID": 1, "species": "PetChibiJinx"}, "gold_left": 6, "last_round": 37, "level": 9, "missions": {"PlayerScore2": 214}, "placement": 3, "players_eliminated": 2, "puuid": "VJb-HCG57UiSBPcSlNTJ95geq_ilMvjxdx5OXG4xxBTu-nkgMmBprkJb8urdYViCZnFeVF6BHMTcpw", "riotIdGameName": "Daddy", "riotIdTagline": "8008", "skill_tree": {"337c74fe-2b61-4d1b-b893-34946f2d3e62": 261, "EventSkill_DemotionProtection": 0, "EventSkill_PlacementDelta": 600, "bb71e7f7-3646-467d-9733-7430e5d42d6a": 150}, "time_eliminated": 2137.915283203125, "total_damage_to_players": 145, "traits": [{"name": "TFT4_Assassin", "num_units": 1, "style": 0, "tier_current": 0, "tier_total": 3}, {"name": "TFT4_Blacksmith", "num_units": 1, "style": 3, "tier_current": 1, "tier_total": 1}, {"name": "TFT4_Cultist", "num_units": 3, "style": 1, "tier_current": 1, "tier_total": 4}, {"name": "TFT4_Daredevil", "num_units": 1, "style": 3, "tier_current": 1, "tier_total": 1}, {"name": "TFT4_Dragonsoul", "num_units": 1, "style": 0, "tier_current": 0, "tier_total": 3}, {"name": "TFT4_Duelist", "num_units": 1, "style": 0, "tier_current": 0, "tier_total": 4}, {"name": "TFT4_Elderwood", "num_units": 1, "style": 0, "tier_current": 0, "tier_total": 3}, {"name": "TFT4_Fortune", "num_units": 1, "style": 0, "tier_current": 0, "tier_total": 3}, {"name": "TFT4_Mystic", "num_units": 1, "style": 0, "tier_current": 0, "tier_total": 4}, {"name": "TFT4_Ninja", "num_units": 1, "style": 1, "tier_current": 1, "tier_total": 2}, {"name": "TFT4_Sharpshooter", "num_units": 1, "style": 0, "tier_current": 0, "tier_total": 3}, {"name": "TFT4_Slayer", "num_units": 6, "style": 2, "tier_current": 2, "tier_total": 3}, {"name": "TFT4_Vanguard", "num_units": 2, "style": 1, "tier_current": 1, "tier_total": 4}, {"name": "TFT4_Warlord", "num_units": 1, "style": 0, "tier_current": 0, "tier_total": 4}], "units": [{"character_id": "TFT4b_Zed", "itemNames": ["TFT_Item_ThiefsGloves", "TFT_Item_BlueBuff", "TFT_Item_GuardianAngel"], "name": "", "rarity": 1, "tier": 2}, {"character_id": "TFT4_Pyke", "itemNames": ["TFT_Item_Bloodthirster", "TFT_Item_GuinsoosRageblade", "TFT_Item_TitansResolve"], "name": "", "rarity": 1, "tier": 2}, {"character_id": "TFT4_Darius", "itemNames": ["TFT_Item_RedBuff", "TFT_Item_TitansResolve", "TFT_Item_TearOfTheGoddess"], "name": "", "rarity": 2, "tier": 2}, {"character_id": "TFT4_Aatrox", "itemNames": ["TFT_Item_ThiefsGloves", "TFT_Item_UnstableConcoction", "TFT_Item_SpectralGauntlet"], "name": "", "rarity": 4, "tier": 2}, {"character_id": "TFT4_Tryndamere", "itemNames": ["TFT_Item_SteraksGage", "TFT_Item_MadredsBloodrazor", "TFT_Item_TearOfTheGoddess"], "name": "", "rarity": 4, "tier": 2}, {"character_id": "TFT4_Olaf", "itemNames": ["TFT_Item_SteraksGage", "TFT_Item_SpearOfShojin", "TFT_Item_Leviathan"], "name": "", "rarity": 4, "tier": 2}, {"character_id": "TFT4_Ornn", "itemNames": [], "name": "", "rarity": 6, "tier": 2}, {"character_id": "TFT4_Samira", "itemNames": ["TFT5_Item_ThiefsGlovesRadiant", "TFT5_Item_TrapClawRadiant", "TFT5_Item_IonicSparkRadiant"], "name": "", "rarity": 6, "tier": 1}, {"character_id": "TFT4_Zilean", "itemNames": [], "name": "", "rarity": 6, "tier": 1}], "win": true}, {"companion": {"content_ID": "1985cab5-1555-40e0-9e61-b2edf8d43a50", "item_ID": 61019, "skin_ID": 19, "species": "PetOwl"}, "gold_left": 71, "last_round": 34, "level": 8, "missions": {"PlayerScore2": 198}, "placement": 4, "players_eliminated": 0, "puuid": "Ubpayed4aLwrUpjGE5qgoR32ykGZaQZGm9GPnP4RrhTcdesoWDZnzXdNn4il6NsZNasZAQXBWJz_jw", "riotIdGameName": "AuntyChrist", "riotIdTagline": "NA1", "skill_tree": {"EventSkill_DemotionProtection": 0, "EventSkill_PlacementDelta": 400}, "time_eliminated": 1989.84716796875, "total_damage_to_players": 96, "traits": [{"name": "TFT4_Assassin", "num_units": 1, "style": 0, "tier_current": 0, "tier_total": 3}, {"name": "TFT4_Brawler", "num_units": 2, "style": 1, "tier_current": 1, "tier_total": 4}, {"name": "TFT4_Duelist", "num_units": 1, "style": 0, "tier_current": 0, "tier_total": 4}, {"name": "TFT4_Emperor", "num_units": 1, "style": 3, "tier_current": 1, "tier_total": 1}, {"name": "TFT4_Fabled", "num_units": 1, "style": 0, "tier_current": 0, "tier_total": 1}, {"name": "TFT4_Fortune", "num_units": 1, "style": 0, "tier_current": 0, "tier_total": 3}, {"name": "TFT4_Keeper", "num_units": 2, "style": 1, "tier_current": 1, "tier_total": 4}, {"name": "TFT4_Sharpshooter", "num_units": 1, "style": 0, "tier_current": 0, "tier_total": 3}, {"name": "TFT4_Slayer", "num_units": 1, "style": 0, "tier_current": 0, "tier_total": 3}, {"name": "TFT4_Vanguard", "num_units": 1, "style": 0, "tier_current": 0, "tier_total": 4}, {"name": "TFT4_Warlord", "num_units": 9, "style": 4, "tier_current": 3, "tier_total": 4}], "units": [{"character_id": "TFT4_Nidalee", "itemNames": [], "name": "", "rarity": 0, "tier": 3}, {"character_id": "TFT4_Garen", "itemNames": ["TFT_Item_WarmogsArmor", "TFT_Item_Redemption", "TFT_Item_GiantsBelt"], "name": "", "rarity": 0, "tier": 2}, {"character_id": "TFT4_JarvanIV", "itemNames": [], "name": "", "rarity": 1, "tier": 1}, {"character_id": "TFT4_Vi", "itemNames": ["TFT_Item_JeweledGauntlet", "TFT_Item_IonicSpark", "TFT_Item_SteraksGage"], "name": "", "rarity": 1, "tier": 3}, {"character_id": "TFT4_Katarina", "itemNames": [], "name": "", "rarity": 2, "tier": 2}, {"character_id": "TFT4_Tryndamere", "itemNames": ["TFT_Item_TitansResolve", "TFT_Item_BFSword"], "name": "", "rarity": 4, "tier": 2}, {"character_id": "TFT4_ChoGath", "itemNames": ["TFT4_Item_WarlordEmblemItem"], "name": "", "rarity": 4, "tier": 2}, {"character_id": "TFT4_Azir", "itemNames": ["TFT_Item_MadredsBloodrazor", "TFT_Item_RabadonsDeathcap", "TFT_Item_AdaptiveHelm"], "name": "", "rarity": 6, "tier": 1}, {"character_id": "TFT4_AzirSoldier", "itemNames": [], "name": "", "rarity": 6, "tier": 1}, {"character_id": "TFT4_AzirSoldier", "itemNames": [], "name": "", "rarity": 6, "tier": 1}], "win": true}, {"companion": {"content_ID": "f130db9f-a102-4dac-be13-e332adb942ff", "item_ID": 79004, "skin_ID": 4, "species": "PetChibiYone"}, "gold_left": 1, "last_round": 37, "level": 9, "missions": {"PlayerScore2": 214}, "placement": 2, "players_eliminated": 1, "puuid": "I2OgAZVPq_KZdV6TqGSy_CVVxzHLpgaTqS31K-W5Xe72-IyHBRYnhYkKjyqySL-nD8RD1dfhLaW5pg", "riotIdGameName": "SumisibakNgPWD", "riotIdTagline": "9507", "skill_tree": {"EventSkill_DemotionProtection": 0, "EventSkill_PlacementDelta": 800}, "time_eliminated": 2139.81787109375, "total_damage_to_players": 126, "traits": [{"name": "TFT4_Adept", "num_units": 3, "style": 2, "tier_current": 2, "tier_total": 3}, {"name": "TFT4_Assassin", "num_units": 1, "style": 0, "tier_current": 0, "tier_total": 3}, {"name": "TFT4_Boss", "num_units": 1, "style": 3, "tier_current": 1, "tier_total": 1}, {"name": "TFT4_Brawler", "num_units": 1, "style": 0, "tier_current": 0, "tier_total": 4}, {"name": "TFT4_Divine", "num_units": 2, "style": 1, "tier_current": 1, "tier_total": 4}, {"name": "TFT4_Duelist", "num_units": 2, "style": 1, "tier_current": 1, "tier_total": 4}, {"name": "TFT4_Enlightened", "num_units": 6, "style": 4, "tier_current": 3, "tier_total": 4}, {"name": "TFT4_Exile", "num_units": 1, "style": 1, "tier_current": 1, "tier_total": 2}, {"name": "TFT4_Mystic", "num_units": 2, "style": 1, "tier_current": 1, "tier_total": 4}, {"name": "TFT4_Ninja", "num_units": 1, "style": 1, "tier_current": 1, "tier_total": 2}, {"name": "TFT4_Syphoner", "num_units": 1, "style": 0, "tier_current": 0, "tier_total": 3}], "units": [{"character_id": "TFT4_Fiora", "itemNames": ["TFT_Item_UnstableConcoction", "TFT_Item_GuinsoosRageblade", "TFT_Item_WarmogsArmor"], "name": "", "rarity": 0, "tier": 2}, {"character_id": "TFT4_Janna", "itemNames": [], "name": "", "rarity": 1, "tier": 2}, {"character_id": "TFT4_Irelia", "itemNames": [], "name": "", "rarity": 2, "tier": 2}, {"character_id": "TFT4_Shen", "itemNames": ["TFT_Item_WarmogsArmor", "TFT_Item_GargoyleStoneplate"], "name": "", "rarity": 4, "tier": 2}, {"character_id": "TFT4b_Morgana", "itemNames": ["TFT_Item_NeedlesslyLargeRod"], "name": "", "rarity": 4, "tier": 2}, {"character_id": "TFT4_Talon", "itemNames": ["TFT_Item_Deathblade", "TFT_Item_InfinityEdge", "TFT_Item_GuardianAngel"], "name": "", "rarity": 4, "tier": 2}, {"character_id": "TFT4_LeeSin", "itemNames": [], "name": "", "rarity": 6, "tier": 1}, {"character_id": "TFT4_Sett", "itemNames": ["TFT5_Item_HandOfJusticeRadiant", "TFT_Item_JeweledGauntlet", "TFT_Item_RabadonsDeathcap"], "name": "", "rarity": 6, "tier": 2}, {"character_id": "TFT4_Yone", "itemNames": ["TFT_Item_Bloodthirster", "TFT_Item_UnstableConcoction"], "name": "", "rarity": 6, "tier": 1}], "win": true}, {"companion": {"content_ID": "5897ad9f-4665-4372-8f3e-6c878adb8918", "item_ID": 1, "skin_ID": 1, "species": "PetTFTAvatar"}, "gold_left": 31, "last_round": 31, "level": 8, "missions": {"PlayerScore2": 91}, "placement": 5, "players_eliminated": 0, "puuid": "LtBHVR9fYTm9XPY9FQyYjQKBub5JkwbsccrNCPINWCzYi-236HdZIaN2AeY3gbhf-FTsASYxb6bC2A", "riotIdGameName": "Markonah", "riotIdTagline": "14045", "skill_tree": {"EventSkill_DemotionProtection": 0, "EventSkill_PlacementDelta": 200}, "time_eliminated": 1820.9893798828125, "total_damage_to_players": 104, "traits": [{"name": "TFT4_Assassin", "num_units": 4, "style": 2, "tier_current": 2, "tier_total": 3}, {"name": "TFT4_Blacksmith", "num_units": 1, "style": 3, "tier_current": 1, "tier_total": 1}, {"name": "TFT4_Cultist", "num_units": 3, "style": 1, "tier_current": 1, "tier_total": 4}, {"name": "TFT4_Divine", "num_units": 1, "style": 0, "tier_current": 0, "tier_total": 4}, {"name": "TFT4_Elderwood", "num_units": 2, "style": 0, "tier_current": 0, "tier_total": 3}, {"name": "TFT4_Executioner", "num_units": 2, "style": 1, "tier_current": 1, "tier_total": 3}, {"name": "TFT4_Fortune", "num_units": 1, "style": 0, "tier_current": 0, "tier_total": 3}, {"name": "TFT4_Keeper", "num_units": 2, "style": 1, "tier_current": 1, "tier_total": 4}, {"name": "TFT4_Ninja", "num_units": 1, "style": 1, "tier_current": 1, "tier_total": 2}, {"name": "TFT4_Slayer", "num_units": 1, "style": 0, "tier_current": 0, "tier_total": 3}, {"name": "TFT4_Spirit", "num_units": 1, "style": 0, "tier_current": 0, "tier_total": 3}, {"name": "TFT4_Vanguard", "num_units": 1, "style": 0, "tier_current": 0, "tier_total": 4}, {"name": "TFT4_Warlord", "num_units": 1, "style": 0, "tier_current": 0, "tier_total": 4}], "units": [{"character_id": "TFT4b_Diana", "itemNames": [], "name": "", "rarity": 0, "tier": 2}, {"character_id": "TFT4_Elise", "itemNames": ["TFT_Item_NightHarvester", "TFT_Item_WarmogsArmor", "TFT_Item_FrozenHeart"], "name": "", "rarity": 0, "tier": 3}, {"character_id": "TFT4_Pyke", "itemNames": [], "name": "", "rarity": 1, "tier": 2}, {"character_id": "TFT4_Akali", "itemNames": ["TFT5_Item_ThiefsGlovesRadiant", "TFT5_Item_IonicSparkRadiant", "TFT5_Item_GuinsoosRagebladeRadiant"], "name": "", "rarity": 2, "tier": 2}, {"character_id": "TFT4_Katarina", "itemNames": ["TFT_Item_JeweledGauntlet", "TFT_Item_TitansResolve"], "name": "", "rarity": 2, "tier": 2}, {"character_id": "TFT4_Kayle", "itemNames": ["TFT_Item_GuinsoosRageblade"], "name": "", "rarity": 4, "tier": 2}, {"character_id": "TFT4_Xayah", "itemNames": ["TFT_Item_GuinsoosRageblade", "TFT_Item_SpearOfShojin", "TFT_Item_Artifact_StatikkShiv"], "name": "", "rarity": 4, "tier": 2}, {"character_id": "TFT4_Ornn", "itemNames": ["TFT_Item_AdaptiveHelm"], "name": "", "rarity": 6, "tier": 1}], "win": false}, {"companion": {"content_ID": "1eeb3ef6-0d35-415b-95ed-718f005ee4e0", "item_ID": 27021, "skin_ID": 21, "species": "PetChoncc"}, "gold_left": 5, "last_round": 37, "level": 9, "missions": {"PlayerScore2": 214}, "placement": 1, "players_eliminated": 3, "puuid": "TRz6ikl7t3N3uaNKJMGfc1bIpg7yhaRRdGJeuvT3kcdnvneaZ-m13sjl6g9X6dyBCb13_FNAvI-HQg", "riotIdGameName": "notsosurelock", "riotIdTagline": "NA1", "skill_tree": {"EventSkill_DemotionProtection": 0, "EventSkill_PlacementDelta": 1000}, "time_eliminated": 2141.3701171875, "total_damage_to_players": 189, "traits": [{"name": "TFT4_Blacksmith", "num_units": 1, "style": 3, "tier_current": 1, "tier_total": 1}, {"name": "TFT4_Brawler", "num_units": 1, "style": 0, "tier_current": 0, "tier_total": 4}, {"name": "TFT4_Daredevil", "num_units": 1, "style": 3, "tier_current": 1, "tier_total": 1}, {"name": "TFT4_Dragonsoul", "num_units": 6, "style": 2, "tier_current": 2, "tier_total": 3}, {"name": "TFT4_Duelist", "num_units": 1, "style": 0, "tier_current": 0, "tier_total": 4}, {"name": "TFT4_Elderwood", "num_units": 1, "style": 0, "tier_current": 0, "tier_total": 3}, {"name": "TFT4_Enlightened", "num_units": 1, "style": 0, "tier_current": 0, "tier_total": 4}, {"name": "TFT4_Sharpshooter", "num_units": 2, "style": 1, "tier_current": 1, "tier_total": 3}, {"name": "TFT4_Slayer", "num_units": 3, "style": 1, "tier_current": 1, "tier_total": 3}, {"name": "TFT4_Syphoner", "num_units": 2, "style": 1, "tier_current": 1, "tier_total": 3}, {"name": "TFT4_Vanguard", "num_units": 2, "style": 1, "tier_current": 1, "tier_total": 4}, {"name": "TFT4_Warlord", "num_units": 1, "style": 0, "tier_current": 0, "tier_total": 4}], "units": [{"character_id": "TFT4_Tristana", "itemNames": ["TFT_Item_StatikkShiv", "TFT_Item_Leviathan", "TFT_Item_GuinsoosRageblade"], "name": "", "rarity": 0, "tier": 3}, {"character_id": "TFT4_Braum", "itemNames": ["TFT_Item_BrambleVest", "TFT_Item_Artifact_LightshieldCrest", "TFT_Item_GargoyleStoneplate"], "name": "", "rarity": 1, "tier": 2}, {"character_id": "TFT4_Shyvana", "itemNames": [], "name": "", "rarity": 2, "tier": 2}, {"character_id": "TFT4_Tryndamere", "itemNames": [], "name": "", "rarity": 4, "tier": 1}, {"character_id": "TFT4_Olaf", "itemNames": ["TFT_Item_TitansResolve", "TFT_Item_Bloodthirster", "TFT_Item_SteraksGage"], "name": "", "rarity": 4, "tier": 1}, {"character_id": "TFT4b_Morgana", "itemNames": [], "name": "", "rarity": 4, "tier": 2}, {"character_id": "TFT4_Ornn", "itemNames": [], "name": "", "rarity": 6, "tier": 1}, {"character_id": "TFT4_Samira", "itemNames": [], "name": "", "rarity": 6, "tier": 1}, {"character_id": "TFT4_Swain", "itemNames": ["TFT_Item_Crownguard", "TFT_Item_HextechGunblade", "TFT_Item_AdaptiveHelm"], "name": "", "rarity": 6, "tier": 2}], "win": true}, {"companion": {"content_ID": "fb19c8b5-a359-4337-b77e-e5c1843c4b47", "item_ID": 47003, "skin_ID": 3, "species": "PetElegantDragon"}, "gold_left": 0, "last_round": 27, "level": 9, "missions": {"PlayerScore2": 78}, "placement": 6, "players_eliminated": 0, "puuid": "Bxy0YkkQBHWuzwUvyWEd9LXlamH4XKhkUO7z1uNSmCiyqL-ruw8HhJcrfNVT1NSoVfCda2_eYJxe5Q", "riotIdGameName": "kimdung", "riotIdTagline": "7196", "skill_tree": {"EventSkill_DemotionProtection": 0, "EventSkill_PlacementDelta": 150}, "time_eliminated": 1572.1500244140625, "total_damage_to_players": 50, "traits": [{"name": "TFT4_Adept", "num_units": 2, "style": 1, "tier_current": 1, "tier_total": 3}, {"name": "TFT4_Assassin", "num_units": 1, "style": 0, "tier_current": 0, "tier_total": 3}, {"name": "TFT4_Cultist", "num_units": 1, "style": 0, "tier_current": 0, "tier_total": 4}, {"name": "TFT4_Divine", "num_units": 3, "style": 1, "tier_current": 1, "tier_total": 4}, {"name": "TFT4_Duelist", "num_units": 6, "style": 4, "tier_current": 3, "tier_total": 4}, {"name": "TFT4_Enlightened", "num_units": 2, "style": 1, "tier_current": 1, "tier_total": 4}, {"name": "TFT4_Executioner", "num_units": 1, "style": 0, "tier_current": 0, "tier_total": 3}, {"name": "TFT4_Exile", "num_units": 1, "style": 1, "tier_current": 1, "tier_total": 2}, {"name": "TFT4_Mystic", "num_units": 1, "style": 0, "tier_current": 0, "tier_total": 4}, {"name": "TFT4_Ninja", "num_units": 1, "style": 1, "tier_current": 1, "tier_total": 2}, {"name": "TFT4_Spirit", "num_units": 2, "style": 1, "tier_current": 1, "tier_total": 3}], "units": [{"character_id": "TFT4b_Diana", "itemNames": ["TFT_Item_JeweledGauntlet"], "name": "", "rarity": 0, "tier": 2}, {"character_id": "TFT4_Yasuo", "itemNames": ["TFT_Item_TitansResolve", "TFT_Item_Bloodthirster"], "name": "", "rarity": 0, "tier": 2}, {"character_id": "TFT4_Fiora", "itemNames": [], "name": "", "rarity": 0, "tier": 2}, {"character_id": "TFT4_Jax", "itemNames": [], "name": "", "rarity": 1, "tier": 2}, {"character_id": "TFT4_Irelia", "itemNames": ["TFT_Item_BrambleVest", "TFT_Item_WarmogsArmor"], "name": "", "rarity": 2, "tier": 2}, {"character_id": "TFT4b_Kindred", "itemNames": [], "name": "", "rarity": 2, "tier": 1}, {"character_id": "TFT4_Kalista", "itemNames": ["TFT_Item_RunaansHurricane", "TFT_Item_GuinsoosRageblade"], "name": "", "rarity": 2, "tier": 2}, {"character_id": "TFT4_Shen", "itemNames": [], "name": "", "rarity": 4, "tier": 1}, {"character_id": "TFT4_LeeSin", "itemNames": ["TFT_Item_Quicksilver"], "name": "", "rarity": 6, "tier": 1}], "win": false}, {"companion": {"content_ID": "3c3e0bf8-c0fb-4dce-8978-7a1f41b0927f", "item_ID": 43012, "skin_ID": 12, "species": "PetJawDragon"}, "gold_left": 18, "last_round": 26, "level": 9, "missions": {"PlayerScore2": 75}, "placement": 8, "players_eliminated": 0, "puuid": "EWXJG0pWwM-xE5QIDIchT7O6JjFGuqoF6zX0Aa_F6QfgZm45m0DREpkApgktQdztEpHQum8WuR9OMQ", "riotIdGameName": "MET", "riotIdTagline": "7782", "skill_tree": {"EventSkill_DemotionProtection": 0, "EventSkill_PlacementDelta": 50}, "time_eliminated": 1516.4071044921875, "total_damage_to_players": 34, "traits": [{"name": "TFT4_Adept", "num_units": 2, "style": 1, "tier_current": 1, "tier_total": 3}, {"name": "TFT4_Assassin", "num_units": 3, "style": 1, "tier_current": 1, "tier_total": 3}, {"name": "TFT4_Boss", "num_units": 1, "style": 3, "tier_current": 1, "tier_total": 1}, {"name": "TFT4_Brawler", "num_units": 1, "style": 0, "tier_current": 0, "tier_total": 4}, {"name": "TFT4_Cultist", "num_units": 1, "style": 0, "tier_current": 0, "tier_total": 4}, {"name": "TFT4_Daredevil", "num_units": 1, "style": 3, "tier_current": 1, "tier_total": 1}, {"name": "TFT4_Enlightened", "num_units": 1, "style": 0, "tier_current": 0, "tier_total": 4}, {"name": "TFT4_Fortune", "num_units": 1, "style": 0, "tier_current": 0, "tier_total": 3}, {"name": "TFT4_Keeper", "num_units": 1, "style": 0, "tier_current": 0, "tier_total": 4}, {"name": "TFT4_Mystic", "num_units": 1, "style": 0, "tier_current": 0, "tier_total": 4}, {"name": "TFT4_Ninja", "num_units": 4, "style": 4, "tier_current": 2, "tier_total": 2}, {"name": "TFT4_Sharpshooter", "num_units": 1, "style": 0, "tier_current": 0, "tier_total": 3}, {"name": "TFT4_Slayer", "num_units": 3, "style": 1, "tier_current": 1, "tier_total": 3}, {"name": "TFT4_Vanguard", "num_units": 1, "style": 0, "tier_current": 0, "tier_total": 4}], "units": [{"character_id": "TFT4b_Zed", "itemNames": ["TFT_Item_PowerGauntlet", "TFT_Item_BlueBuff", "TFT_Item_Quicksilver"], "name": "", "rarity": 1, "tier": 1}, {"character_id": "TFT4_Pyke", "itemNames": [], "name": "", "rarity": 1, "tier": 1}, {"character_id": "TFT4_Akali", "itemNames": ["TFT_Item_SpearOfShojin", "TFT_Item_Leviathan", "TFT_Item_HextechGunblade"], "name": "", "rarity": 2, "tier": 1}, {"character_id": "TFT4_Kennen", "itemNames": [], "name": "", "rarity": 2, "tier": 1}, {"character_id": "TFT4_Sejuani", "itemNames": [], "name": "", "rarity": 4, "tier": 1}, {"character_id": "TFT4_Shen", "itemNames": ["TFT_Item_IonicSpark"], "name": "", "rarity": 4, "tier": 2}, {"character_id": "TFT4_Talon", "itemNames": [], "name": "", "rarity": 4, "tier": 1}, {"character_id": "TFT4_Sett", "itemNames": [], "name": "", "rarity": 6, "tier": 1}, {"character_id": "TFT4_Samira", "itemNames": [], "name": "", "rarity": 6, "tier": 1}], "win": false}], "queueId": 6110, "queue_id": 6110, "tft_game_type": "standard", "tft_set_core_name": "TFTSet4_Act2", "tft_set_number": 4}}